Metadata-Version: 1.0
Name: spammer
Version: 0.0.1
Summary: spamming for discord or minecraft
Home-page: UNKNOWN
Author: UNKNOWN
Author-email: UNKNOWN
License: UNKNOWN
Platform: UNKNOWN
